easy_graphql_server/__init__.py
easy_graphql_server/casing.py
easy_graphql_server/context.py
easy_graphql_server/conversion.py
easy_graphql_server/custom_json.py
easy_graphql_server/exceptions.py
easy_graphql_server/exposition.py
easy_graphql_server/graphql_types.py
easy_graphql_server/introspection.py
easy_graphql_server/model_config.py
easy_graphql_server/model_config_custom_field.py
easy_graphql_server/operations.py
easy_graphql_server/py.typed
easy_graphql_server/schema.py
easy_graphql_server/testing.py
easy_graphql_server/types.py
easy_graphql_server/orm/__init__.py
easy_graphql_server/orm/_fields.py
easy_graphql_server/orm/_lookups.py
easy_graphql_server/orm/_manager.py
easy_graphql_server/orm/django_errors.py
easy_graphql_server/orm/django_manager.py
easy_graphql_server/orm/peewee_manager.py
easy_graphql_server/orm/sqlalchemy_manager.py
easy_graphql_server/webserver/__init__.py
easy_graphql_server/webserver/_schema_view.py
easy_graphql_server/webserver/django_schema_view.py
easy_graphql_server/webserver/flask_schema_view.py
easy_graphql_server/webserver/static/__init__.py
easy_graphql_server/webserver/static/graphiql.html
easy_graphql_server-0.9.31.dist-info/LICENCE
easy_graphql_server-0.9.31.dist-info/METADATA
easy_graphql_server-0.9.31.dist-info/WHEEL
easy_graphql_server-0.9.31.dist-info/top_level.txt
easy_graphql_server-0.9.31.dist-info/RECORD
