Metadata-Version: 2.1
Name: easy-graphql-server
Version: 0.9.31
Summary: Easy to use abstraction layer for GraphQL, with support for Django ORM.
Home-page: https://github.com/mathieurodic/easy-graphql-server
Author: Mathieu Rodic
Author-email: graphql@rodic.fr
License: MIT license
Project-URL: Bug Tracker, https://github.com/mathieurodic/easy-graphql-server/-/issues
Keywords: graphql django
Classifier: Development Status :: 5 - Production/Stable
Classifier: Intended Audience :: Developers
Classifier: Topic :: Software Development :: Libraries
Classifier: License :: OSI Approved :: MIT License
Classifier: Programming Language :: Python :: 3
Classifier: Programming Language :: Python :: 3 :: Only
Classifier: Programming Language :: Python :: 3.6
Classifier: Programming Language :: Python :: 3.7
Classifier: Programming Language :: Python :: 3.8
Classifier: Programming Language :: Python :: 3.9
Classifier: Programming Language :: Python :: 3.10
Requires-Python: >=3.6,<4
License-File: LICENCE
Requires-Dist: graphql-core (==3.1.7)
Provides-Extra: tests
Requires-Dist: django (==3.2) ; extra == 'tests'
Requires-Dist: faker (==11.1.0) ; extra == 'tests'
Requires-Dist: flask (==2.0.2) ; extra == 'tests'
Requires-Dist: flask-login (==0.5.0) ; extra == 'tests'
